{"breaks":[{"minute":45,"duration":4,"scene_hint":"Family gathering and initial ghostly encounters.","miss_risk":"Low"},{"minute":85,"duration":4,"scene_hint":"Investigation into the palace's history and escalating supernatural activity.","miss_risk":"Mid"},{"minute":125,"duration":5,"scene_hint":"Unraveling the mystery and confronting the entity.","miss_risk":"Low"}],"best_break":45,"runtime_min":173,"conservative_breaks":[{"minute":45,"duration":4,"scene_hint":"Family gathering and initial ghostly encounters.","miss_risk":"Low"},{"minute":125,"duration":5,"scene_hint":"Unraveling the mystery and confronting the entity.","miss_risk":"Low"}],"relaxed_breaks":[{"minute":45,"duration":4,"scene_hint":"Family gathering and initial ghostly encounters.","miss_risk":"Low"},{"minute":65,"duration":3,"scene_hint":"Exploring hidden parts of the palace and discovering clues.","miss_risk":"Mid"},{"minute":85,"duration":4,"scene_hint":"Investigation into the palace's history and escalating supernatural activity.","miss_risk":"Mid"},{"minute":125,"duration":5,"scene_hint":"Unraveling the mystery and confronting the entity.","miss_risk":"Low"}]}